lsb/__init__.py
lsb/actions.py
lsb/admin.py
lsb/apps.py
lsb/constants.py
lsb/crypto.py
lsb/exceptions.py
lsb/forms.py
lsb/list_filters.py
lsb/managers.py
lsb/models.py
lsb/py.typed
lsb/serializers.py
lsb/tests.py
lsb/views.py
lsb/ddragon/__init__.py
lsb/ddragon/_ddragon.py
lsb/ddragon/_skins.py
lsb/migrations/0001_initial.py
lsb/migrations/0002_product_country.py
lsb/migrations/0003_product_summoner_name.py
lsb/migrations/0004_product_ban_reason_product_date_banned_and_more.py
lsb/migrations/0005_product_division_product_is_handleveled_product_rank.py
lsb/migrations/0006_product_is_auth_error.py
lsb/migrations/0007_product_flash_key.py
lsb/migrations/0008_product_losses_product_wins.py
lsb/migrations/0009_rename_losses_product_solo_losses_and_more.py
lsb/migrations/0010_product_lsb_product_region_d31e5c_idx_and_more.py
lsb/migrations/0011_product_is_bare_metal.py
lsb/migrations/0012_product_city_product_date_sign_up_product_dob_and_more.py
lsb/migrations/0013_product_is_disabled_product_remarks.py
lsb/migrations/0014_product_date_checked.py
lsb/migrations/0015_product_status.py
lsb/migrations/0016_product_disabled_until.py
lsb/migrations/0017_remove_product_is_disabled.py
lsb/migrations/0018_alter_product_rank.py
lsb/migrations/0019_product_date_last_played.py
lsb/migrations/0020_alter_product_rank.py
lsb/migrations/0021_alter_product_region.py
lsb/migrations/0022_alter_product_blue_essence_alter_product_level_and_more.py
lsb/migrations/0023_product_is_proxmox.py
lsb/migrations/0024_product_is_safe.py
lsb/migrations/0025_alter_product_is_safe.py
lsb/migrations/0026_product_uploaded_by.py
lsb/migrations/0027_product_is_aram_only_product_is_recovery_requested.py
lsb/migrations/0028_alter_product_is_recovery_requested.py
lsb/migrations/0029_product_is_current_season_rank.py
lsb/migrations/0030_product_date_password_checked.py
lsb/migrations/0031_product_quickplay_losses_product_quickplay_wins.py
lsb/migrations/0032_alter_product_region_alter_skin_tier.py
league_shop_base-1.0.80.dist-info/METADATA
league_shop_base-1.0.80.dist-info/WHEEL
league_shop_base-1.0.80.dist-info/top_level.txt
league_shop_base-1.0.80.dist-info/RECORD
