Metadata-Version: 2.1
Name: league-shop-base
Version: 1.0.80
Summary: Base models and admin for league-shop
Author-email: Pradish Bijukchhe <pradish@sandbox.com.np>
Project-URL: Homepage, https://github.com/sandbox-pokhara/league-shop-base
Project-URL: Issues, https://github.com/sandbox-pokhara/league-shop-base/issues
Classifier: Programming Language :: Python :: 3
Requires-Python: >=3
Requires-Dist: cryptography
Requires-Dist: django-advanced-search
Requires-Dist: django-form-action>=2.0.0
Requires-Dist: django-form-button>=1.0.0
Requires-Dist: django-stubs-ext
Requires-Dist: Django<5,>=3.1
Requires-Dist: djangorestframework
Requires-Dist: pytz
Requires-Dist: requests-futures
